{"fountains":0,"tables":0,"chairs":0,"pools":3,"layout":[{"x":77,"y":83.40625,"width":50,"height":50,"typeI":"greenSquare"},{"x":85,"y":240.40625,"width":50,"height":50,"typeI":"greenSquare"},{"x":82,"y":354.40625,"width":50,"height":50,"typeI":"greenSquare"},{"x":80,"y":429.40625,"width":50,"height":50,"typeI":"greenSquare"},{"x":245,"y":118.40625,"width":150,"height":100,"typeO":"pool","typeI":"blueRectangle"},{"x":244,"y":234.40625,"width":150,"height":100,"typeO":"pool","typeI":"blueRectangle"},{"x":247,"y":348.40625,"width":150,"height":100,"typeO":"pool","typeI":"blueRectangle"}]}